pyconju/__init__.py
pyconju/csv.py
pyconju/xls.py
pyconju/xlsx.py
pyconju-0.1.2.dist-info/LICENSE
pyconju-0.1.2.dist-info/METADATA
pyconju-0.1.2.dist-info/WHEEL
pyconju-0.1.2.dist-info/top_level.txt
pyconju-0.1.2.dist-info/RECORD
