Metadata-Version: 2.1
Name: pyconju
Version: 0.1.2
Summary: Python package for merging multiple files
Home-page: https://github.com/dyagee/pyconju
Download-URL: https://github.com/dyagee/pyconju/archive/refs/tags/v0.1.2.tar.gz
Author: Agee Aondo
Author-email: ageeaondo45@gmail.com
Project-URL: Bugs, https://github.com/dyagee/pyconju/issues
Project-URL: Docs, https://pyconju.readthedocs.io/
Keywords: python3,excel,xls,csv,xlsx,merge
Classifier: Programming Language :: Python :: 3
Classifier: License :: OSI Approved :: MIT License
Classifier: Operating System :: OS Independent
Classifier: Natural Language :: English
Classifier: Topic :: Software Development :: Libraries :: Python Modules
Classifier: Intended Audience :: Developers
Classifier: Intended Audience :: Science/Research
Classifier: Intended Audience :: Other Audience
Requires-Python: >=3.7
License-File: LICENSE
Requires-Dist: pandas
Requires-Dist: openpyxl
Requires-Dist: xlrd (==2.0.1)
